mlvision/augmentation.py
mlvision/datasets.py
mlvision/distributed.py
mlvision/logger.py
mlvision/models/__init__.py
mlvision/models/cnn.py
mlvision/models/mobileone.py
mlvision/optim.py
mlvision/train.py
mlvision-0.1.0.dist-info/METADATA
mlvision-0.1.0.dist-info/WHEEL
mlvision-0.1.0.dist-info/entry_points.txt
mlvision-0.1.0.dist-info/RECORD
