Metadata-Version: 2.1
Name: mlvision
Version: 0.1.0
Summary: 
Author: Guichard Victor
Author-email: guichardvictor@gmail.com
Requires-Python: >=3.10,<4.0
Classifier: Programming Language :: Python :: 3
Classifier: Programming Language :: Python :: 3.10
Classifier: Programming Language :: Python :: 3.11
Requires-Dist: pyyaml (>=6.0,<7.0)
Requires-Dist: torch (>=2.0.1,<3.0.0)
Requires-Dist: torchvision (>=0.15.2,<0.16.0)
